vtai/__init__.py
vtai/app.py
vtai/assistants/manager.py
vtai/assistants/mino/__init__.py
vtai/assistants/mino/assistant_event_handler.py
vtai/assistants/mino/create_assistant.py
vtai/assistants/mino/mino.py
vtai/assistants/shared/__init__.py
vtai/assistants/tools/__init__.py
vtai/assistants/tools/web_search.py
vtai/resources/vt.jpg
vtai/resources/screenshot/1.jpg
vtai/resources/screenshot/2.jpg
vtai/resources/screenshot/3.jpg
vtai/resources/screenshot/4.png
vtai/router/__init__.py
vtai/router/constants.py
vtai/router/layers.json
vtai/router/trainer.py
vtai/tools/__init__.py
vtai/tools/search.py
vtai/utils/__init__.py
vtai/utils/api_compatibility.py
vtai/utils/assistant_tools.py
vtai/utils/chat_profile.py
vtai/utils/config.py
vtai/utils/constants.py
vtai/utils/conversation_handlers.py
vtai/utils/dict_to_object.py
vtai/utils/error_handlers.py
vtai/utils/file_handlers.py
vtai/utils/llm_profile_builder.py
vtai/utils/llm_providers_config.py
vtai/utils/media_processors.py
vtai/utils/safe_execution.py
vtai/utils/settings_builder.py
vtai/utils/starter_prompts.py
vtai/utils/url_extractor.py
vtai/utils/user_session_helper.py
vtai-0.7.2.dist-info/METADATA
vtai-0.7.2.dist-info/WHEEL
vtai-0.7.2.dist-info/entry_points.txt
vtai-0.7.2.dist-info/licenses/LICENSE
vtai-0.7.2.dist-info/RECORD
