Metadata-Version: 2.4
Name: vtai
Version: 0.7.2
Summary:  VT.ai - Minimal multimodal AI chat app with dynamic conversation routing 
Project-URL: Homepage, https://github.com/vinhnx/VT.ai
Project-URL: Bug Tracker, https://github.com/vinhnx/VT.ai/issues
Author: Vinh Nguyen
License: MIT
License-File: LICENSE
Classifier: Development Status :: 4 - Beta
Classifier: License :: OSI Approved :: MIT License
Classifier: Operating System :: OS Independent
Classifier: Programming Language :: Python :: 3
Classifier: Programming Language :: Python :: 3.11
Classifier: Topic :: Scientific/Engineering :: Artificial Intelligence
Requires-Python: >=3.11
Requires-Dist: chainlit>=2.0.0
Requires-Dist: google-generativeai>=0.3.0
Requires-Dist: httpx>=0.26.0
Requires-Dist: litellm>=1.30.0
Requires-Dist: openai>=1.20.0
Requires-Dist: pillow>=10.0.0
Requires-Dist: pydantic==2.10.1
Requires-Dist: python-dotenv>=1.0.0
Requires-Dist: semantic-router[fastembed]>=0.0.54
Requires-Dist: tavily-python>=0.5.4
Provides-Extra: dev
Requires-Dist: black>=23.7.0; extra == 'dev'
Requires-Dist: flake8>=6.1.0; extra == 'dev'
Requires-Dist: isort>=5.12.0; extra == 'dev'
Requires-Dist: pytest-asyncio>=0.26.0; extra == 'dev'
Requires-Dist: pytest>=8.3.5; extra == 'dev'
Requires-Dist: twine>=6.1.0; extra == 'dev'
Provides-Extra: docs
Requires-Dist: mkdocs-llmstxt>=0.2.0; extra == 'docs'
Provides-Extra: http2
Requires-Dist: h2>=4.1.0; extra == 'http2'
Requires-Dist: httpx[http2]>=0.26.0; extra == 'http2'
